cv_smart_house_camera/__init__.py
cv_smart_house_camera/cam_capture.py
cv_smart_house_camera/constants.py
cv_smart_house_camera/data/frames.py
cv_smart_house_camera/database/cv-smarthouse-firebase-adminsdk-kwy7w-db7a30b68e.json
cv_smart_house_camera/database/database.py
cv_smart_house_camera/generate_code.py
cv_smart_house_camera/helpers/poetry_install.py
cv_smart_house_camera/init_server.py
cv_smart_house_camera/main.py
cv_smart_house_camera/modules/modules_list.py
cv_smart_house_camera/modules/modules_processing.py
cv_smart_house_camera/proto_services/camera_service_pb2.py
cv_smart_house_camera/proto_services/camera_service_twirp.py
cv_smart_house_camera/server.py
cv_smart_house_camera/utils/get_local_ip.py
cv_smart_house_camera/utils/get_modules_from_toml.py
cv_smart_house_camera/webrtc/create_offer.py
cv_smart_house_camera-0.1.9.4.1.dist-info/entry_points.txt
cv_smart_house_camera-0.1.9.4.1.dist-info/METADATA
cv_smart_house_camera-0.1.9.4.1.dist-info/WHEEL
cv_smart_house_camera-0.1.9.4.1.dist-info/RECORD
